{
  "targetingScopeDmg": "1",
  "tagbackGrenadeMarks": "1",
  "newtonMaxDistance": "3",

  "initialRAmmo": "1",
  "initialBAmmo": "1",
  "initialYAmmo": "1",
  "killShotTrackPoints1": "5",
  "killShotTrackPoints2": "4",
  "killShotTrackPoints3": "3",
  "killShotTrackPoints4": "2",
  "killShotTrackPoints5": "1",
  "killShotTrackPointDecrease1": "2",
  "killShotTrackPointDecrease2": "1",
  "maximumDmg": "12",
  "lethalDmg": "11",
  "maximumMarks": "3",
  "adrenaline1Dmg": "3",
  "adrenaline2Dmg": "6",
  "maxWeapons": "3",
  "initialPUToDraw": "2",

  "status": [
    {
      "elementId": "0",
      "numberOfActions": "3",
      "steps1": "3",
      "steps2": "1",
      "steps3": "0",
      "collect1": "0",
      "collect2": "1",
      "collect3": "0",
      "shoot1": "0",
      "shoot2": "0",
      "shoot3": "1",
      "reload1": "0",
      "reload2": "0",
      "reload3": "0"
    },

    {
      "elementId": "1",
      "numberOfActions": "3",
      "steps1": "3",
      "steps2": "2",
      "steps3": "0",
      "collect1": "0",
      "collect2": "1",
      "collect3": "0",
      "shoot1": "0",
      "shoot2": "0",
      "shoot3": "1",
      "reload1": "0",
      "reload2": "0",
      "reload3": "0"
    },
    {
      "elementId": "2",
      "numberOfActions": "3",
      "steps1": "3",
      "steps2": "2",
      "steps3": "1",
      "collect1": "0",
      "collect2": "1",
      "collect3": "0",
      "shoot1": "0",
      "shoot2": "0",
      "shoot3": "1",
      "reload1": "0",
      "reload2": "0",
      "reload3": "0"
    },
    {
      "elementId": "3",
      "numberOfActions": "3",
      "steps1": "4",
      "steps2": "2",
      "steps3": "1",
      "collect1": "0",
      "collect2": "1",
      "collect3": "0",
      "shoot1": "0",
      "shoot2": "0",
      "shoot3": "1",
      "reload1": "0",
      "reload2": "0",
      "reload3": "1"
    },
    {
      "elementId": "4",
      "numberOfActions": "2",
      "steps1": "3",
      "steps2": "2",
      "collect1": "1",
      "collect2": "0",
      "shoot1": "0",
      "shoot2": "1",
      "reload1": "0",
      "reload2": "1"
    }
  ]

}